{
  "schemaVersion": 1,
  "id": "princerupertsbedrock",
  "version": "${version}",

  "name": "Prince Rupert's Bedrock",
  "description": "A Vanilla+ method for Bedrock removal inspired by the mechanics of Prince Rupert's Drop!",
  "authors": [
    "Aug"
  ],
  "contact": {
    "homepage": "https://github.com/Augumat/prince-ruperts-bedrock",
    "sources": "https://github.com/Augumat/prince-ruperts-bedrock"
  },

  "license": "MIT",
  "icon": "assets/princerupertsbedrock/icon.png",

  "environment": "*",
  "entrypoints": {
    "main": [
      "com.aug.princerupertsbedrock.PrinceRupertsBedrock"
    ]
  },
  "mixins": [
    "princerupertsbedrock.mixins.json"
  ],

  "depends": {
    "fabricloader": ">=0.11.3",
    "fabric": "*",
    "minecraft": "1.18.x",
    "java": ">=17"
  },
  "suggests": {
    "another-mod": "*"
  }
}
